video_vocal_rt/__init__.py
video_vocal_rt/experiment.py
video_vocal_rt-0.4.0.dist-info/LICENSE.md
video_vocal_rt-0.4.0.dist-info/METADATA
video_vocal_rt-0.4.0.dist-info/WHEEL
video_vocal_rt-0.4.0.dist-info/RECORD
