Metadata-Version: 2.1
Name: video-vocal-rt
Version: 0.4.0
Summary: Video-Vocal-RT: a minimal package for vocal response to video
Home-page: https://github.com/LoonanChauvette/video-vocal-RT
License: MIT
Keywords: video,audio,psychology,reaction time
Author: Loonan Chauvette
Author-email: loonan.chauvette@gmail.com
Requires-Python: >=3.10,<3.12
Classifier: Development Status :: 2 - Pre-Alpha
Classifier: Intended Audience :: Science/Research
Classifier: License :: OSI Approved :: MIT License
Classifier: Natural Language :: English
Classifier: Operating System :: OS Independent
Classifier: Programming Language :: Python :: 3
Classifier: Programming Language :: Python :: 3.10
Classifier: Programming Language :: Python :: 3.11
Classifier: Topic :: Multimedia :: Sound/Audio
Classifier: Topic :: Multimedia :: Video
Requires-Dist: ffpyplayer (>=4.5.0,<5.0.0)
Requires-Dist: moviepy (>=1.0.3,<2.0.0)
Requires-Dist: numpy (>=1.24.2,<2.0.0)
Requires-Dist: opencv-python (>=4.7.0.72,<5.0.0.0)
Requires-Dist: openpyxl (>=3.1.2,<4.0.0)
Requires-Dist: pillow (<10.0.0)
Requires-Dist: pysimplegui (>=4.60.4,<5.0.0)
Requires-Dist: scipy (>=1.10.1,<2.0.0)
Requires-Dist: sounddevice (>=0.4.6,<0.5.0)
Project-URL: Repository, https://github.com/LoonanChauvette/video-vocal-RT
